extract_from_url/__init__.py
extract_from_url-0.3.0.dist-info/LICENSE
extract_from_url-0.3.0.dist-info/WHEEL
extract_from_url-0.3.0.dist-info/METADATA
extract_from_url-0.3.0.dist-info/RECORD
