Metadata-Version: 2.1
Name: extract-from-url
Version: 0.3.0
Summary: Download and extract files on-the-fly (ZIP files too)
Home-page: https://github.com/frafra/extract-from-url
License: GPL-3.0+
Keywords: libarchive-c
Author: Francesco Frassinelli
Author-email: francesco.frassinelli@nina.no
Requires-Python: >=3.7,<4.0
Classifier: License :: OSI Approved :: GNU General Public License v3 or later (GPLv3+)
Classifier: Programming Language :: Python :: 3
Classifier: Programming Language :: Python :: 3.7
Classifier: Programming Language :: Python :: 3.8
Classifier: Programming Language :: Python :: 3.9
Classifier: Programming Language :: Python :: 3.10
Requires-Dist: fs (>=2.0.0)
Requires-Dist: libarchive-c (>=1.0)
Project-URL: Repository, https://github.com/frafra/extract-from-url
